{"config": {"view": {"continuousWidth": 300, "continuousHeight": 300}}, "data": {"name": "data-5b2bb3cd460ab7702ab2cb58d32f8642"}, "mark": {"type": "bar"}, "encoding": {"color": {"field": "Book", "type": "nominal"}, "column": {"field": "Character", "header": {"labelOrient": "bottom", "titleOrient": "bottom"}, "type": "nominal"}, "tooltip": [{"field": "Book", "type": "nominal"}, {"field": "Character", "type": "nominal"}, {"field": "Rate (per 10k words)", "format": ".2f", "type": "quantitative"}], "x": {"field": "Character", "sort": "-y", "type": "nominal"}, "y": {"field": "Rate (per 10k words)", "type": "quantitative"}}, "params": [{"name": "param_1", "select": {"type": "interval", "encodings": ["x", "y"]}, "bind": "scales"}], "title": "Change in Main Character Name Usage", "$schema": "https://vega.github.io/schema/vega-lite/v5.20.1.json", "datasets": {"data-5b2bb3cd460ab7702ab2cb58d32f8642": [{"Book": "Fellowship", "Character": "frodo", "Rate (per 10k words)": 57.38400392979949}, {"Book": "TheKing", "Character": "frodo", "Rate (per 10k words)": 28.59545836837679}, {"Book": "Fellowship", "Character": "sam", "Rate (per 10k words)": 22.105122136381905}, {"Book": "TheKing", "Character": "sam", "Rate (per 10k words)": 33.714849892127106}, {"Book": "Fellowship", "Character": "pippin", "Rate (per 10k words)": 11.610771223150092}, {"Book": "TheKing", "Character": "pippin", "Rate (per 10k words)": 20.62383442425129}, {"Book": "Fellowship", "Character": "merry", "Rate (per 10k words)": 12.280623409101057}, {"Book": "TheKing", "Character": "merry", "Rate (per 10k words)": 16.893992028376054}, {"Book": "Fellowship", "Character": "gandalf", "Rate (per 10k words)": 24.728709864689858}, {"Book": "TheKing", "Character": "gandalf", "Rate (per 10k words)": 22.3790543752514}, {"Book": "Fellowship", "Character": "aragorn", "Rate (per 10k words)": 11.16420309918278}, {"Book": "TheKing", "Character": "aragorn", "Rate (per 10k words)": 16.45518704062603}, {"Book": "Fellowship", "Character": "boromir", "Rate (per 10k words)": 8.261510293395258}, {"Book": "TheKing", "Character": "boromir", "Rate (per 10k words)": 1.9746224448751235}, {"Book": "Fellowship", "Character": "gimli", "Rate (per 10k words)": 6.475237797526012}, {"Book": "TheKing", "Character": "gimli", "Rate (per 10k words)": 5.631330676125352}, {"Book": "Fellowship", "Character": "legolas", "Rate (per 10k words)": 5.247175456615906}, {"Book": "TheKing", "Character": "legolas", "Rate (per 10k words)": 4.899989029875306}, {"Book": "Fellowship", "Character": "bilbo", "Rate (per 10k words)": 13.508685750011164}, {"Book": "TheKing", "Character": "bilbo", "Rate (per 10k words)": 2.413427432625151}, {"Book": "Fellowship", "Character": "elrond", "Rate (per 10k words)": 6.754342875005582}, {"Book": "TheKing", "Character": "elrond", "Rate (per 10k words)": 2.413427432625151}, {"Book": "Fellowship", "Character": "galadriel", "Rate (per 10k words)": 2.1211985888447282}, {"Book": "TheKing", "Character": "galadriel", "Rate (per 10k words)": 1.6089516217501005}, {"Book": "Fellowship", "Character": "faramir", "Rate (per 10k words)": 0.0}, {"Book": "TheKing", "Character": "faramir", "Rate (per 10k words)": 11.84773466925074}, {"Book": "Fellowship", "Character": "denethor", "Rate (per 10k words)": 0.33492609297548337}, {"Book": "TheKing", "Character": "denethor", "Rate (per 10k words)": 8.849233919625553}, {"Book": "Fellowship", "Character": "eowyn", "Rate (per 10k words)": 0.0}, {"Book": "TheKing", "Character": "eowyn", "Rate (per 10k words)": 0.0}, {"Book": "Fellowship", "Character": "theoden", "Rate (per 10k words)": 0.0}, {"Book": "TheKing", "Character": "theoden", "Rate (per 10k words)": 0.0}]}}